seasonwatch/__init__.py
seasonwatch/app.py
seasonwatch/cli.py
seasonwatch/config.py
seasonwatch/constants.py
seasonwatch/exceptions.py
seasonwatch/media_watcher.py
seasonwatch/sql.py
seasonwatch/utils.py
seasonwatch-0.3.0.dist-info/METADATA
seasonwatch-0.3.0.dist-info/WHEEL
seasonwatch-0.3.0.dist-info/entry_points.txt
seasonwatch-0.3.0.dist-info/RECORD
