Metadata-Version: 2.1
Name: seasonwatch
Version: 0.3.0
Summary: A script to let you know when there are new seasons of your TV shows
License: GPL-3.0
Author: Simon
Author-email: gevhaz@tutanota.com
Requires-Python: >=3.9,<4.0
Classifier: License :: OSI Approved :: GNU General Public License v3 (GPLv3)
Classifier: Programming Language :: Python :: 3
Classifier: Programming Language :: Python :: 3.9
Classifier: Programming Language :: Python :: 3.10
Classifier: Programming Language :: Python :: 3.11
Classifier: Programming Language :: Python :: 3.12
Requires-Dist: PyGObject (>=3.42.1,<4.0.0)
Requires-Dist: PyYAML (>=6.0,<7.0)
Requires-Dist: apsw (>=3.38.5,<4.0.0)
Requires-Dist: colorama (>=0.4.5,<0.5.0)
Requires-Dist: prettytable (>=3.7.0,<4.0.0)
Requires-Dist: python-dateutil (>=2.8.2,<3.0.0)
Requires-Dist: requests (>=2.31.0,<3.0.0)
